{"Романов Михаил Федорович": [3, 181, 1004], "Евдокия": [4, 98], "Лев": [4, 5, 23, 38, 46, 99, 143, 156, 398, 587, 1205], "Иван": [4, 5, 23, 90, 100, 137, 143, 377, 382, 418, 529, 605, 1205, 1560, 1741, 1747, 1749], "Лева": [19, 28, 31, 42, 75, 143, 159, 201, 286, 293, 297, 302, 325, 330, 334, 337, 339, 345, 382, 391, 467, 574, 575, 608, 611, 612, 614, 640, 906, 1061, 1098, 1099, 1181, 1183, 1248, 1344, 1386, 1392, 1398], "Тамара Головина": [22], "Гриша Шаховский": [24, 800], "Гриша": [26, 802, 819, 827], "Ванька Голицын": [27, 385], "Ванька": [28, 57, 71, 239, 244, 255, 265, 271, 297, 300, 301, 333, 391, 476, 581, 669], "Иван Михайлович": [33, 133, 135, 174, 195, 196, 208, 210, 215, 243, 245, 258, 307, 309, 552, 688, 1398], "Вань": [34, 537], "Ольга": [34, 109], "Задорнов": [35, 41], "Ваня": [36, 38, 145], "Минин": [39, 237, 552, 704], "Пожарский": [39, 237, 552, 704], "Лжедмитрий II": [39, 227, 228, 550], "Тушинским": [39], "Василий Шуйский": [40, 122, 124, 179, 215, 220, 226, 228, 684, 696, 700, 707, 1322], "Дмитрий": [41, 54, 56, 120, 122, 123, 124, 161, 204, 213, 215, 219, 449, 450, 478, 482, 717, 729], "Волдыевский": [54, 160], "Что-о-о": [59], "Левкино": [60, 583], "Широков Савелий Михайлович": [66], "Савелий": [66, 67, 69, 73, 84, 85, 86, 89, 94, 113, 115, 126, 130, 131, 133, 137, 145, 147, 149, 152, 154, 159, 160, 165, 172, 177, 180, 346, 359, 364, 408, 424, 429, 445, 457, 463, 501, 509, 514, 518, 641, 645, 790, 874, 877, 884, 885, 1066, 1067, 1211, 1231, 1236, 1252, 1290, 1368, 1431, 1435, 1436, 1438, 1443, 1445, 1452, 1460], "Неелов": [72], "Левая": [78, 714], "Михаил": [86, 88, 114, 157, 1205, 1322], "Федор": [86, 212, 1095], "Михаил Федорович Романов": [98], "Анастасия": [99], "Ксения": [100, 389, 394, 523, 1523, 1573], "Трубецкой Никита Романович": [101, 241, 294, 1779], "Голицын Иван Васильевич": [102, 294, 523], "Молчанов Михаил Андреевич": [103], "Антонина": [104, 671, 820, 916, 962, 1061, 1075, 1082, 1085, 1181, 1327, 1328, 1331, 1384, 1537, 1539], "Шаховский Григорий Петрович": [105, 294], "Елена": [105], "Головин Семен Васильевич": [106], "Тамара": [106, 149, 406, 957], "Мстиславский Федор Иванович": [107], "Галина": [108, 149, 405, 954, 1334], "Воротынский Иван Михайлович": [109, 118, 159, 294, 1396], "Лыков Борис Михайлович": [110, 294], "Дешковский Петр Иванович": [114, 404], "Петр Иванович": [115], "Михаил Федорович": [115, 116, 160, 161, 172, 347, 359, 363, 408, 463, 642, 887, 1015, 1247, 1255, 1297, 1779, 1786, 1796], "Иван Васильевич": [119, 381, 523, 567], "Иван Васильевича": [119], "Дмитрий Иванович": [119, 122, 163, 167, 213, 222, 223, 228], "Гришка Отрепьев": [120, 223], "Маринке Мнишек": [121], "Дешковский": [125], "Петр": [131, 155], "Лобанов Иван": [131, 136, 169, 361], "Приданный": [146], "Мишка": [149], "Дьяк": [152], "Прокопий": [159, 163, 167], "Барков Федор Семенович": [159], "Кезолин Лука Иванович": [159], "Федор Семенович": [162, 346, 348, 353, 455], "Шуйский": [163, 699, 702], "Василий": [167, 359, 360, 450, 451, 452, 479, 482, 553, 623, 631, 639, 683, 699, 716, 717], "Лука Иванович": [170, 346, 361, 409, 422], "Барков": [171, 180], "Вон Михаил Федорович": [172], "Урал": [175], "Лжедмитрием II": [176], "Кезолин": [180], "Мишаня": [185, 293, 296, 438], "Никита Романович": [192, 247, 250, 253, 275, 276, 278, 283, 289, 798, 824, 865, 1229], "Карл IX": [206, 553], "Сигизмунд III": [206, 222, 232, 235, 553, 1322, 1952], "Иван Грозный": [212], "Борис Годунов": [212, 213, 218, 223, 225], "Мария Нагой": [213], "Федор Иванович": [213], "Борис Федорович Годунов": [215], "Борис": [215], "Годуновым": [215], "Смутное": [221], "Годунова": [222], "Юрий Мнишек": [222], "Лев Сапегой": [222], "Адам": [222], "Константин Вишневецкими": [222], "Лжедмитрий I": [225, 699], "Владислав": [235, 702], "Воротынского": [239], "Григорий Петрович Шаховский": [260], "Том": [262], "Трубецкой": [266, 282, 288, 290, 385, 817, 832, 838, 840, 846, 849, 855, 859, 950, 1227, 1785], "Сталин": [273, 867], "Григорий Петрович": [287, 324, 334, 337], "Семен Васильевич": [287], "Борис Михайлович": [287], "Головин Иван Васильевич": [294], "Ванькина": [299, 389], "Леву": [306], "Лев Федорович": [311, 324, 357], "Фергюсон": [319, 331, 388, 390, 468, 574], "Иван Федорович": [351, 445, 1253], "Ваньшу Савелий": [367], "Голицын": [381], "Мишка Молчанов": [385, 620], "Головин Семен": [385], "Федька Мстиславский": [385, 620, 1339], "Борька Лыков": [385, 475], "Ксанка": [389, 391], "Левой": [391], "Ну Ванечка": [393], "Настя": [394, 1395, 1835], "Левкина": [394], "Гришка Шаховской": [396, 596], "Гришке": [397], "Ванечка": [398, 668, 669, 768, 1325, 1383, 1384, 1387], "Гришка": [399, 441, 442, 901, 1099], "Анфиса": [405, 523], "Василиса": [405, 523], "Галкиным": [406], "Хитро": [422], "Головастый": [442], "Фергюсон Гришка": [444], "Скопин-Шуйский": [452, 453, 517, 553, 554, 590, 623, 631, 636, 639, 663, 664, 684, 694, 696, 697, 699, 706, 707, 1322, 1952], "Ксюха": [470, 536, 546, 579, 580, 583, 586, 912], "Петр Дешковском": [471], "Василич": [528, 742, 893, 894, 1093, 1405], "Григорий Шаховской": [530], "Михаил Васильевич Скопин-Шуйский": [550], "Филарет": [551], "Романов": [551, 1014, 1020, 1029, 1107, 1119, 1124, 1127, 1130, 1136, 1148, 1412, 1414, 1423, 1604, 1606, 1611, 1776, 1779, 1793, 1799, 1940, 1942, 1944, 1945, 1953], "Шуйский Василий Иванович": [552], "Делагарди": [553, 637, 640, 683], "Михаил Васильевич": [555, 557, 562, 564, 592, 698, 699, 701, 716, 717, 719, 720, 721, 728, 732, 1323], "Хейердал": [569], "Суворов": [577], "Левки": [581], "Левка": [586], "Мишань": [591], "Шереметев": [592, 680], "Кернозицкий": [593, 624], "Колумб": [601, 774, 1053], "Санта-Марии": [601], "Эк": [607], "Ванькой": [618], "Кернозицкого": [624], "Старая Руссу": [624, 625], "Зборовский": [627, 631, 661], "Головин": [628], "Горн": [628], "Князь": [637, 664, 712], "Калязин": [639], "Савелию": [660], "Ольга Воротынская": [660], "Ян Сапеги": [661], "Фридрих I": [664], "Наполеон I": [664], "Сапеги": [666, 681], "Левушки": [668], "Ваньку": [670], "Маринку Мнишек": [673], "Скопина-Шуйского": [680, 683, 1951], "Лисовский": [681], "Гермоген": [682], "Лжедмитрий": [682, 704], "Воротынским Иван Михайлович": [687], "Прокопий Ляпунов": [699], "Екатерина Шуйская": [700], "Воротынский": [701, 717, 721, 726, 729, 830, 847, 1217, 1222, 1234], "Скопину-Шуйскому": [701], "Сигизмунд": [702], "Михаил Романов": [704], "Романовых": [705], "Голштейн-Готторп": [705], "Романовы": [707], "Петр I": [707, 980], "Николай II": [707], "Скопин-Шуский": [711], "Мишаней": [714, 1879], "Катька Шуйская": [717, 721, 729], "Скопина-Шуйский": [721], "Александрова": [728], "Наталья Борисовна": [736], "Елизавета I": [745, 1056, 1949], "Френсис Дрейк": [745, 774, 1053, 1056], "Девиса": [752], "Галилео Галилей": [756], "Василичем": [763], "Васко да Гама": [774], "Магеллан": [774], "Филипп III": [777, 1602], "Генрих IV Наваррского": [779], "Людовик XIII": [779], "Мария Медичи": [779], "Генрих Наваррский": [779], "Генрих IV": [780], "Стюартов": [783], "Яков I Стюарт": [783], "Савелий Михайлович": [785, 786, 857, 1253], "Николай": [785, 786, 790, 812, 857, 874, 1066, 1211, 1236, 1243, 1252, 1253, 1319, 1431, 1682, 1686], "Иван Михайлович Воротынский": [794], "Никита Романович Трубецкой": [796], "Дрейк": [804, 1360], "Шаховский": [814], "Ватсон": [816], "Катрина": [819], "Луизиан": [820], "Антонина Молчанова": [821], "Марк Твен": [824], "Антонин": [828, 1081], "Никита": [844, 850, 851, 893, 915, 951, 956, 971, 977, 978, 994, 1003, 1036, 1093, 1101, 1103, 1219, 1233, 1345, 1358, 1376, 1398, 1402, 1669, 1671, 1680, 1687, 1787, 1797], "Эх": [853], "Сема": [902], "Ванек": [909], "Гриня": [912], "Левушка": [916, 1385], "Галина Мстиславская": [951, 1192], "Устюжинским": [966], "Вон": [988], "Гоголь": [992], "Фернандо Гонсалес де Агилар": [1002, 1146, 1601], "Игнасио Кано Диас": [1006, 1034, 1106], "Мария": [1006], "Америками": [1040], "Игнасио": [1043, 1108, 1112, 1114, 1162, 1163, 1416], "Новоустюжинском": [1060], "Ай да Федька": [1091], "Дизель-то": [1092], "Мстиславский": [1093], "Шаховской": [1099, 1343], "Григорий": [1100], "Генерал-капитан": [1117], "Фернандо": [1162, 1415, 1424, 1600, 1602, 1609, 1612, 1788, 1802, 1935, 1941, 1943, 1945, 1948], "Филипп де Агилар": [1164], "Филипп": [1165], "Джордж Вашингтон": [1171], "Антонины": [1185], "Сторожевой": [1186], "Боря Лыков": [1197], "Мутно": [1212], "Никита Трубецкой": [1212], "Парящий Орел": [1249, 1255], "Майор Романов": [1276], "Михаил Романович": [1293], "Гольфстрим": [1314], "Куса": [1328], "Сторожевого": [1350], "Антониной": [1353, 1354], "Дашковский Петр Иванович": [1372], "Вон Антонина": [1375], "Радость-то": [1383], "Иван Иванович": [1383], "Семен": [1387, 1547, 1549, 1552], "Настю Романову": [1392], "Михаил Холмогорского": [1408], "Сеньор Фернандо Гонсалес де Агилар": [1411], "Приватирский": [1421], "Джонатан Эшли": [1421], "Генерал-губернатор": [1425], "Парящим Орел": [1428], "Парящего Орел": [1430, 1475], "Парящему Орел": [1462], "Вождь": [1463], "Сильный Ветер": [1465], "Танцующий": [1471, 1488], "Быстрый Поток": [1473, 1864, 1981], "Танцующий Огонь": [1473, 1640], "Теть Оль": [1505], "Прохор": [1526], "Лужецкий Семен Иванович": [1546], "Фергюссона": [1563], "Сеньор Фернандо": [1603], "Кастилии": [1714], "Командир": [1732, 1740], "де Агилар": [1779], "Отлично": [1802], "Весельчаку": [1815], "Сержант": [1885], "Никифор": [1903, 1905, 1907], "Не": [1921, 1931, 1932], "Ай да Ванька": [1947], "Воротынские": [1951], "Трубецкие": [1951]}