{"Кот": [8, 11], "Алиса": [10], "Зелененькая": [30], "Зелененькие": [35], "Шарк": [36], "Вон": [48, 518, 617, 710, 726, 799, 886, 1015, 1399, 1704, 3344, 4044, 4100, 7967, 9884, 9893, 10472, 10736], "Мультяшка": [50, 116, 118, 124, 141, 170, 173, 548, 581, 596, 600, 1679, 2799, 4229, 4604, 4779, 5420], "О! Заверещали": [51], "Токо": [56], "Гонсалес": [60], "Ким РэВон": [60], "Мун ДжонХо": [60, 7865, 7866], "Ким ВонХэ": [60], "Кимы": [60, 5563], "Паки": [60], "Моргаю": [61], "Симпатяшка": [74], "Колобок": [105, 272, 277, 299, 301, 317, 396, 399, 400, 402, 403, 405, 10059], "Чебурашки": [132], "Малевич": [132, 135], "Макаренко": [135], "Шин Джи Мин": [136, 138, 197, 437, 538, 1007, 1233, 5503], "Умгукаю": [136], "Сун Чон Хян": [137, 139, 222], "Шин ДжиМин": [139, 5626, 5840, 7894], "Бу-бу": [169], "Кора": [169], "Тамара": [173], "Кивает": [197], "Холмс": [199], "Клубничкой": [213], "Радистка Кэт": [215], "Хан КоНиль": [218, 722, 1006, 1472, 2011, 4758, 4788, 5626, 5840, 7866, 7894, 7915, 8253, 8259, 8962, 9393], "Хам": [218], "Ватсон": [224], "Марсель Марсо": [224, 7657], "Гераклы": [238], "Федя": [240, 885], "ВИП-ов": [341], "Очкарик": [351], "Инглиш": [361], "Блиин": [371, 442], "Мультяшке": [377], "Хан СынХен": [379, 663, 671, 1225, 7894, 7911], "Хан ЧжиХе": [379, 1225], "Рыбка": [381], "Билы Гейтсы": [382], "Дергаю": [392], "Ли": [401, 2231, 2242, 2783, 4351, 4374, 6061], "Фикс": [422], "Хан": [437, 473, 1686], "Папаша": [439, 579], "Хаха": [466], "Ким Вон Хэ": [477, 479], "Вертинский": [500], "Хихи": [501], "Торописся": [506, 543], "Ли Стефани": [510, 719, 722, 723, 1177, 1366, 1469, 1472, 1474, 2220, 2222, 2274, 2580, 3523, 3906, 3907, 8547], "Блииин": [518, 3904], "Чет": [547, 1535], "Маршал": [570], "Челентано": [570], "Кристофер Марло": [584], "Сота Фукуси": [585], "Кобр": [604], "Кобром": [609], "Высоцкий": [613], "Ян Мин Хэ": [661, 1214], "Пан Гималайский": [664], "Чхве Тэ Ен": [680, 885, 921, 1181], "ВИП-мадам": [706, 966], "Кунфу": [733], "Хисасибури дэсу Фукуси-сэмпай": [751], "Матанэ": [766], "Потешно": [769], "Форест Гамп": [769], "Билли": [769], "Карабасы-Барабасы": [793], "Сеньоры Помидоры": [793], "Дубина": [796], "Топаем": [818], "Эээ-тян": [831, 1270, 2345], "О! Отмер": [853], "Чжи У-ян": [887, 894], "Трус": [891], "Слушающий Эээ-тян": [902], "Кан Ен Гю": [941, 958, 1203, 1257, 1945, 2007], "Сэнсэй Кан Ен Гю": [945], "Стефани": [966, 1020, 1140, 1476, 1482, 1487, 2240, 2241, 3158, 6381, 6765], "Чжон A Ми": [968, 977, 1000, 1045, 1082, 1166, 1409, 1476, 1741], "Джи Мин-тян": [1007], "СМС-ка": [1080], "Жан Эффель": [1085], "Леонардо": [1085], "Микеланджело": [1085, 4556], "Скользкий": [1097, 1099, 1107, 1785], "Хен": [1106, 1430, 4743, 5430, 6046, 6054, 6185, 6192, 6218, 6395, 6397, 6925, 6930, 6993, 7480, 7593, 7599, 7652, 8079, 8337, 8531, 8727, 8744, 8750, 9188, 9190, 9985], "Микки": [1114], "Самсунг (Samsung Life Insurance)": [1117], "Нанкин": [1126], "Кун": [1127], "Путунхуа": [1133], "О! Железяки": [1143], "Незнайки": [1168], "Гэн И": [1173, 1250, 1256, 1873, 2802], "Паустовского": [1190], "КоНиль": [1212, 1216, 1785, 1805, 1862, 1907, 2012, 2373, 2982, 3519, 6791, 6891], "Хан Гю Вон": [1227, 3180], "Чхве Хи Джин": [1230, 3180], "Чхан Хен": [1283], "Гю Вон-яна": [1283], "Хан Гю Вон-сии": [1283], "Савонарола": [1292], "Шнитке": [1292], "Гершвин": [1292], "Баюн": [1297], "Баян": [1297], "Боян": [1297], "Кузьма": [1304], "Отличное": [1319, 4142, 4982, 9679, 10556, 11185], "Внучок": [1324], "Кеши": [1331], "То-есть": [1383], "Здоровое": [1398, 9718], "Сэнсэй": [1407], "Хи Джин": [1413, 1512, 1584, 1936], "Отелло": [1413], "Морозов": [1423], "Николаев": [1423], "Иди-ка": [1429], "Хе": [1434], "Остряки": [1436], "Леонид": [1511], "Хан Чхан Хен": [1511], "Кэрролл": [1515], "Аркадий Райкин": [1536], "Ладушки": [1538, 1796], "Ржевский": [1577], "Берт Рутан": [1584], "Илон Маск": [1584], "Джимми Хендрикс": [1616, 1950, 1970, 4248], "Рур": [1649], "Цузе": [1649], "Таак": [1675, 7621], "Малышка": [1680], "Монтекки": [1686], "Капулетти": [1686], "ЫнДжон": [1691, 2207, 2274, 2277, 2282, 5207, 5275, 5607, 5628, 5657, 5661, 5668, 5675, 5796, 5799, 5805, 6790, 6914, 7398, 7476, 8289, 8327, 8488, 8518, 8528, 8538, 8720, 8926, 10328, 10513, 10515], "Пэ менджин": [1738], "Ким СоХи": [1738, 1858, 3180], "Кан енгю": [1739, 2311], "КоНиль-ян": [1759, 2240], "Вон менджин-ян": [1778], "ЧжиУ-ян": [1782, 1804], "ГюВон": [1787, 1790, 1871, 1958, 2449, 3033], "ГюВон-ом": [1793, 1804], "Зануда": [1795, 1871, 1891, 1896, 1897, 1904, 1939, 2043, 2516, 2633, 3361, 4173, 4489, 4947, 5104, 5422, 8962, 10221], "Эээ-ян": [1797], "ЧжиУ": [1809, 1901], "Сокчхо Хан КоНиля": [1809], "Вестибубилюбибу": [1814, 1815, 1831, 1832, 1848, 1849], "Чжон Чхан Хва": [1856, 2808, 3169, 3178], "ХиДжин": [1865, 1981, 2003, 2300, 3361, 6876], "СоХи": [1879, 1986, 2154], "Чжон А Ми": [1883, 1942, 1943, 2219, 2249, 2508, 3176, 3179, 3187, 3264, 3955], "менджин": [1884, 2042, 2516, 2934, 2988, 3542], "КоНиля": [1888, 3396, 7894], "Зануды": [1905, 3295, 3367, 4176, 9561, 9595], "Чхан Хва": [1906, 6409, 7502], "Го": [1908], "Ходжа Насреддин": [1941], "Монмартр": [1943], "Эл Ди Миола": [1944], "Солирует ХиДжин": [1985], "Че": [1987], "Бобби МакГи": [2014, 2269, 3644, 3655, 3669, 3672, 4167, 8059, 8061], "Саджан-ним Мак Ги": [2014], "Тут Здоровяк": [2020], "Бобби": [2031, 2033, 2037, 2265, 2266, 2267, 2268, 2269, 2272, 2373, 2374, 2501, 2502, 2511, 3644, 3648, 3653, 3667, 4171, 4174, 4175, 8059, 8063, 8064], "Марта": [2031, 2033, 2036, 2268, 2373], "менджин-у": [2042], "СоНии": [2075, 2605, 2939], "СонМун": [2075, 2156, 2422, 3004], "Баламут": [2095, 2119, 2122, 2632], "СоМун-ом": [2124], "Соллаль": [2194], "Пусанские": [2204], "Хан КоНиль-ян": [2219], "Шин ДжиМин-тян": [2219], "Пен ХиСон": [2242], "Самоним Ли": [2242], "Дженис Джоплин": [2269, 2272], "Кристоферсон": [2272], "Фостер": [2272], "Трейни": [2274], "Марта МакГи": [2300], "Классно": [2356], "Шекспир": [2379], "Маршак": [2379, 10274], "Пастернак": [2379, 10274], "МинХек-а": [2420], "Точно": [2424], "Дед": [2424], "МинХек-у": [2435], "Вон МинХек": [2437], "Карл": [2470], "Ханок": [2495], "Вест": [2576], "Гейтс": [2578], "Джобс": [2578], "Джесси Кук": [2582, 2583], "Деми Ловато": [2583], "ГюВон-а": [2605], "Сунын": [2627, 5304], "Маман": [2628], "Чжон ЧханХва": [2730], "Маугли": [2737, 8400], "Видик": [2803], "Чеджу": [2828, 3137], "Чжон Ами": [2829, 3138], "Изабель Койшет": [2873], "Изабель": [2877, 2878, 2892, 2894, 2907, 2909, 2914, 2916, 2918, 2921, 2936, 2949, 2966, 2991, 2999, 3000, 3031, 4521], "Ии": [2889, 5662, 9476, 10200], "Розины": [2898], "Бомарше": [2898], "Диктатор' Коэн": [2903], "Дорн": [2903], "Погуляли": [2905], "СоМун": [2940, 2942], "Бамболео": [2963, 2965, 2967, 2969, 7724], "Знающий Зануда": [2978], "Лопе де Вега": [2998], "ДаБин": [3046, 3054, 4095], "Майя": [3106, 3108, 3109, 3112, 3116], "Хоан Мануэль Серрат": [3130], "Юрий Сенкевич": [3135], "Дмитрий Крылов": [3135], "Хосе": [3171, 3963, 3993, 7360, 11179], "Тотошки": [3175], "Чжон Чхан Хвану": [3176], "Чжон Чхван Хва": [3179, 3206, 3264], "Ча Ю Ми": [3180, 3182, 3198, 3204, 3205, 3215, 3223, 3264, 3275, 3278, 3280, 3283, 3284, 3974, 4419, 7104], "Пэ Да Бин": [3180], "Пэ Мен Джин": [3180], "Чхон Сон Мун": [3180], "Чжон": [3180], "Хан Ко Ниль": [3180], "Ча Кван Хен": [3185], "Уважаемый Чжон Чхван Хва": [3216], "Ами-ссии": [3222], "хемин": [3242], "Госпожа Ча Ю Ми": [3276], "ЮМи": [3285, 3598, 3902, 3906, 3975, 3977, 3978, 3991, 4474, 5450, 5470, 7502, 7683, 7734, 8337, 8349, 8404, 10744], "Гад": [3345], "Джи Мин": [3345, 3558, 9369], "Братик": [3431], "Хорошенькая": [3458], "Ча ЮМи": [3461], "Ушки": [3473], "Кажется ЕнБин": [3492], "ЕнБин": [3513], "Привет КванХен-ян": [3528], "гювон": [3542], "Онни": [3565, 4910, 5273, 5701, 5761, 5800, 6031, 6318, 6533, 6695, 7404, 7810], "Чон Борам": [3569, 3573], "Борам": [3586, 5349, 8140, 10345], "Ким": [3590, 5563, 6025, 6034, 6832, 6844, 6849, 6877, 7303, 7304, 7313, 7518, 7529, 7538, 7915, 7967, 8333], "Юми": [3594, 6394, 6396], "Самуил Яковлевич": [3599], "Сонсэнним Чжон АМи": [3608], "Неуловимый Джо": [3612], "Майю": [3614, 7534], "Золушку": [3617], "Дон Жуан": [3685], "Жуан": [3687], "Мигель": [3688, 3990, 4521, 5476, 5544, 7693, 7719], "Марко": [3688, 3694, 3980, 3985, 3986, 4519, 4521, 5444, 5449, 9657, 9659, 9670, 9673, 9687, 9691, 9693, 9705, 9707, 9708, 10159], "Финикийский Гадир": [3700], "Ипполит Матвеевич": [3705], "Киса": [3705], "Кошмарики": [3714], "Корона": [3753, 3789, 3832, 3840, 3877, 3912, 4016, 4098, 4459, 5771, 8318, 8853], "СоЕн": [3754, 3764, 3832, 3851, 5022, 5594, 6905, 7314, 8561, 10112, 10115, 10138, 10343, 10346, 10355, 10395, 10401, 10408, 10410, 10427, 10456, 10531, 10555], "КюРи": [3754, 3761, 3765, 3884, 4118, 4912, 4965, 5345, 5349, 5611, 5614, 5632, 5657, 5661, 5672, 5684, 5702, 5784, 5810, 5814, 6100, 6110, 6114, 6140, 6414, 6530, 6685, 6821, 6826, 6827, 6896, 7474, 8133, 8172, 8330, 8559, 8759, 9021, 9891, 9923, 10357, 10435], "Мм... КюРи": [3764], "Оптимистка": [3802], "Бедная СоЕн": [3841], "Чжон АМи": [3906, 5680, 5681, 7021], "Сек": [3936], "Туан": [3936], "Трэй": [3937], "Привет Мигель": [3944], "Хосе Монхе Крус": [3955], "Хоаким Албаисин": [3955], "Хоаким": [3963, 3980], "Вонг": [3975], "Николя": [3985, 3989, 3990, 3995, 4001, 4002, 5452, 5543, 5544], "Старшие": [3987], "Хосе Крус": [3992, 10472, 11160], "Евроньюс": [4022], "Руби": [4045], "А-вариант": [4059], "А-уровень": [4064], "Грейт Бритн": [4082, 6654], "Гэн И.": [4169, 4175], "Зануде": [4197], "Харлей": [4199, 4230, 4523, 8775, 8778, 8939], "Хен Гю": [4206, 4230], "Смешарики": [4222], "Кван Хен": [4235], "Сон Мун": [4243], "Карлсон": [4286, 5449], "Сабоним Хан Тхэ Иль": [4321], "Хан Тхэ Иль": [4352, 7000, 7915], "ВИП-семейству": [4471], "Пак Джин Ен": [4487, 9790, 9794], "Мария": [4521], "Табаки": [4521], "Кордоба": [4528, 4535], "Особенно": [4546], "Варфоломей": [4556], "Борис Носик": [4563], "Александр I": [4565], "Миттеран": [4566], "Музык": [4582], "Мишель": [4595, 4602, 4609, 4637, 4641, 4647, 4648, 9125, 9130, 9167], "Брассанс": [4597], "Дассена": [4607], "Ален Женестар": [4644, 7148], "Кан Йе Бин": [4646, 9125], "Опаньки": [4647], "Хан Джин": [4648], "Джин-ян": [4650], "Врядли": [4711], "Вот-ведь": [4731], "Юсон": [4737, 5543, 6052, 6215, 6249, 6324, 6331, 6401, 6930, 6960, 6990, 7595, 7649, 7662, 8726, 8733, 8749, 8877, 9145, 9172, 9184, 10008, 10013, 10051, 10052, 10522, 10527, 10532, 10534], "Хевон": [4737, 5425, 5469, 6049, 6210, 6400, 6936, 7644, 8005], "Нури": [4738, 5428, 5474, 6041, 6053, 6216, 6249, 6385, 6405, 6525, 6933, 6935, 6987, 6991, 7303, 7597, 7650, 7663, 7819, 7936, 8083, 8524, 8535, 8730, 8869, 9172, 9177, 9197, 9595, 10002], "Канэн": [4739, 6048, 6217, 6387, 6507, 6928, 7480, 7602, 7651, 7940, 8873, 9196, 10742], "Амино": [4740, 5547, 5548, 6047, 6211, 6389, 6937, 6961, 7645, 7670, 8881], "Сони": [4741, 6043, 6051, 6129, 6192, 6212, 6386, 6927, 7594, 7601, 7646, 8005, 8536, 8745, 8885, 9195], "Джин": [4745, 4749, 5429, 6128, 6200, 6398, 6400, 6492, 6551, 6586, 6701, 6705, 6987, 7001, 7002, 7017, 7018, 7022, 7044, 7105, 7431, 7438, 7603, 7642, 7664, 7670, 7676, 7705, 7817, 7894, 7937, 8006, 8044, 8087, 8111, 8286, 8291, 8292, 8560, 8590, 8688, 8693, 8706, 8719, 8723, 8734, 8749, 8865, 8925, 8957, 8960, 8962, 8966, 9016, 9065, 9073, 9110, 9112, 9113, 9125, 9165, 9177, 9184, 9188, 9192, 9196, 9197, 9320, 9399, 9406, 9435, 9436, 9444, 9445, 9452, 9454, 9478, 9513, 9548, 9585, 9593, 9596, 9602, 9641, 9657, 9658, 9668, 9669, 9677, 9684, 9687, 9688, 9689, 9690, 9692, 9697, 9707, 9709, 9713, 9748, 9751, 9752, 9755, 9766, 9771, 9786, 9851, 9852, 9854, 9856, 9901, 9903, 9907, 9909, 9911, 9915, 9919, 9922, 9927, 9929, 9945, 9984, 10034, 10042, 10115, 10221, 10230, 10234, 10251, 10496, 10498, 10509, 10516, 10537, 10645, 10741, 10744, 10803, 10816, 10897, 10928, 10971, 10978, 10994, 11132, 11164, 11167], "Виктор Иммануил II": [4755, 4766], "Луиза Винчи": [4758], "Винчи": [4761], "Лучана": [4778], "Лучана Серра": [4791], "О! Мультяшка": [4826], "Нифиг": [4830], "Сеньорина": [4956], "Круууто": [4995, 5718], "Тото Кутуньо": [5060], "Шут": [5095], "Лисенок": [5098], "Портье": [5173], "Кипеловская": [5174], "По-корейски": [5200], "ХеМин": [5259, 5610, 5632, 5661, 5674, 5724, 5736, 5764, 5773, 5792, 5814, 5836, 5853, 5859, 5861, 5874, 5885, 5905, 5908, 5915, 6030, 6796, 6964, 6966, 7474, 7504, 8132, 8302, 8343, 8344, 8350, 8423, 8448, 8540, 8925, 9163, 9224, 9231, 9449, 9550, 9904, 10219, 10537, 10682, 10701], "Занудой": [5282], "Макнэ": [5296, 10216], "Тамошнему ВОГу": [5343], "БоРам": [5402, 5404, 8994, 8995, 10106], "Соня": [5422, 5452, 5543, 6190, 7303, 9192, 10457], "Канэна": [5429], "С ЮМи": [5454], "Луиджи": [5503], "Брааатик": [5516], "Лючана": [5516], "Папа Карло": [5519], "Ни-за-что": [5522], "Ким Хен Ра": [5563], "Не-на-вижу": [5601], "Ексоль": [5618], "Хмм": [5626], "Белоголовый": [5672, 5677, 5723], "Подожди ЫнДжон": [5685], "Мурано": [5713], "Ын Джон": [5774, 9900, 9902, 9904], "Онниии": [5797], "боры": [5814], "Рик Вэйкман": [5831], "Пак Су Вон": [5840], "Пак СуВон": [5852], "ХеМин-ов": [5856], "Шиза": [5917, 10313, 10592, 10731], "Чха СынВон": [6084], "К-поп": [6093, 6380, 6508, 6541, 6863, 6886, 7146, 8236, 8276], "Бррр": [6100], "Вини": [6125], "Упс": [6168], "Хена": [6187], "Пол": [6187], "Нопфлера": [6194], "Умница Нури": [6281], "Иван Вабищевич": [6298], "Василий Туркин": [6298], "Тимофей Копылов": [6332, 8867], "Госпожа Ли Стефани": [6377], "Клиповые": [6380], "А 'Деспасито": [6397], "Трофим": [6424], "Ярослав Дронов": [6429], "Ксана Сергиенко": [6504], "Хэвон": [6509, 6960, 7480, 7600, 9189, 9193], "Ривз": [6509], "Молодец Хэвон": [6524], "Хо-хо": [6556, 7678], "Клиповый": [6575], "Лист": [6579], "О! Смотри-ка": [6580], "Рояль": [6589], "Сергей Ручкин": [6618], "Василий Уриевский 'Я": [6618], "Наргиз Закиров": [6703], "Везунчики": [6802], "Мультяшку": [6849, 7502], "Пэ ДонгВон": [6960], "Нуна": [6971], "Шин Сон Ю": [6999], "Хан Тхэ Илю": [7012], "Адриано Челентано": [7026, 7635], "Джулиано": [7028, 7031], "Остап": [7047], "Беспечный Ездок": [7071], "Джин-а": [7116], "Пэ Джон Пок Вы": [7135], "Коэн": [7208, 7298], "Балабол": [7220], "Макс Фадеев": [7238], "Гант": [7309], "Шустрый": [7487], "Багира": [7502], "Балу": [7502], "Зепп-холлов": [7512], "Кавасаки": [7530, 7531, 7536], "Гайдаевский Шурик": [7536], "Тсс": [7546], "Вертер": [7571], "Мангэля": [7657], "Хо-ха": [7661], "Солируют Канэн": [7670], "Джииин": [7713, 8427], "Чириби": [7724], "Джина": [7811, 8174, 8711, 8926, 9260, 9297, 9315, 9360, 9645, 9863, 10238, 11201], "Файтин": [7820, 7821], "Расул Гамзатов": [7861, 10870], "Сунчонхян": [7865], "Огава Ясуши": [7879, 7894, 7903, 7908], "Согласитесь Огава-сан": [7882], "Огава-сан": [7910], "Федор": [7964], "Шарик": [7964], "Сэм": [7970], "А. Крупнов": [8003], "МинХеК-у": [8013], "Бони Тайлер": [8032], "Маришку": [8032], "Байкер": [8040], "Хей": [8059], "Эмиль Кадыров": [8061], "Март": [8064], "Кое-кто": [8070], "Ирина Буренкова": [8075], "Дронов Норов": [8089], "Хлюп": [8125, 9892, 10704], "Подлиза": [8180], "Прибила": [8188], "Джин.": [8222], "Во-во": [8233], "Фукусимских": [8248], "У 'Короновок": [8276], "Сандра": [8276], "Пол Анка": [8278], "Армик": [8279], "Валерий Сюткин": [8308], "к-поп-": [8337], "Станиславский": [8344], "Ермолова": [8344], "Книппер-Чехов": [8344], "Бал": [8353], "Багирой": [8353], "Милан": [8355], "Гималайский": [8386], "ДжиИн": [8391, 8419, 8926, 9452, 9603, 11064], "АМи-сии": [8424], "Хачатурян": [8432], "Маскарад": [8432], "Носков": [8435, 8441], "Шахерезада": [8455], "Юрий Левитанский": [8461], "ЮМи-ссии": [8503], "Нью Йоркер": [8571], "Пьер Эдель": [8579], "Америкэн Инквайер": [8582], "Короли Свинг": [8593], "Мюзик Авардс": [8603], "К-Поп": [8746], "Барби": [8760], "Слоны": [8765], "Харлеи": [8766], "Харлей! Карл": [8774], "Майн Рид": [8775], "Бон Джови!": [8810], "Сергеев Замулина": [8851], "Нана Хатл": [8851], "Рамин Альханский": [8871], "Михаил Озеров": [8875], "Кайрат Примбердиев": [8879, 8915], "Ольга Задонская": [8883], "Браво Амино": [8889], "Эльмира Калимуллина": [8891], "Гарипова Минина Озеров": [8909], "Надежда Константиновне": [8919], "Инессе Арманд": [8919], "Клейн": [8949], "Джиин": [8961], "Ну Юсон": [9117], "Фроло": [9117, 9145], "Сердобольная ХеМин": [9129], "Несравненная": [9143], "Эсмеральда": [9143], "Феб - Нури": [9144], "Майкл Джексон": [9169], "Цыганка ДжиЕн": [9172], "Фролло": [9177], "Юсону": [9177], "Жиль Майо": [9177], "Ну Хен": [9193], "Джи Ен": [9207, 9210], "Вот Джи Ен": [9208], "Рамазотти": [9231], "Рикки": [9231], "Повери": [9231], "Шепчу": [9252], "Чонен": [9308, 9384, 9386, 9583, 9585, 9590, 9592, 9594, 9596, 9601, 9643, 9731, 9737, 9742, 9745, 9753, 9757, 9881, 9886, 9890, 9895, 9898, 9914, 10189, 10202, 10207, 10245, 10251, 10257], "Цзыюн": [9308, 9384, 9386, 9556, 9560, 9561, 9565, 9571, 9573, 9576, 9587, 9592, 9593, 9596, 9641, 9732, 9733, 9739, 9747, 9749, 9750, 9751, 9757, 9772, 9774, 9783, 9785, 9790, 9791, 9793, 9794, 9796, 9797, 9810, 9811, 9812, 9813, 9814, 9869, 9870, 9875, 9881, 9883, 9885, 9888, 9892, 9897, 9913, 9918, 9924, 10210, 10218, 10230, 10245, 10251, 10257, 10258, 10272, 10282, 10284, 10289, 10564, 10590, 10609, 10628, 10637, 10643, 10646, 10664, 10668, 10679, 10689, 10694, 10696, 10700, 10701, 10709], "Собственно СБ-шник": [9324], "Помнящие Миланская": [9337], "Ю Чонг": [9349], "Бай": [9356], "Кстати Ю Чонг": [9378], "Неплохо": [9388], "Молодец": [9508], "Сана": [9510, 9732, 9740, 9746, 9756, 10213, 10228, 10238, 10241, 10256], "Миланская": [9531], "Покрасневшая Цзыюн": [9601], "Зульфия": [9618], "Шьет Гюли": [9619], "Спасибо Марко": [9669], "Андреа": [9680, 9696, 9699, 9704, 9713, 9724, 9725, 10102, 10112, 10114, 10115, 10116, 10117, 10133, 10136, 10138, 10164, 10475, 10908, 11188], "Андреа Бочелли": [9680, 9695, 10099, 10144, 11160], "Господин Бочелли": [9698], "Момо": [9734, 9738, 9748, 9750, 9754, 10229, 10258], "Мина": [9736, 9758, 10215, 10246, 10276], "Тайванка Цзыюн": [9807], "Тайванку": [9837], "Спасибо Джин": [9863], "Вдруг ХеМин": [9873], "О! Братишка": [9877], "Синяки": [9904], "Медик": [9905], "Хе Мин": [9905], "Привет Джин": [9914, 10564], "Джину": [9916], "Марк": [9991, 10870], "Вали": [9991], "Фил": [9992, 9993], "Смит": [9996, 9997], "Фукусимские": [10017], "Превосходно": [10029], "Мао": [10033], "Звотнила ДжиЕн": [10041], "Сынри": [10054, 10055, 10059, 10078, 10079, 10091, 10092, 10094, 10098, 10360], "Паваротти": [10102], "Бочелли": [10114], "Нино Рота": [10115, 10116, 10117, 10120, 10122, 10157, 10221, 10472, 10538, 10715, 10722, 10723, 10777, 10896, 11160], "Нино": [10117, 10133, 10164, 10465, 10545, 10786, 10789, 10802, 10808, 10817, 10900, 10901, 10966, 11143, 11179, 11216], "Вальс Цветов": [10120], "Бетховен": [10127], "Рота": [10129], "Хан КоНиля": [10136], "Дуэт c Сони": [10148], "Гаф": [10198], "Капитан": [10221], "Особенно 'Баламут": [10256], "Владимир Высоцкий": [10265], "Дахен": [10276], "Данил Плужников": [10279], "Михаил Боярский": [10311], "Никита Поздняков": [10339], "Вчера СоЕн": [10345], "Леопольд": [10371], "Светлая": [10427], "Привет Сонечка": [10428], "сойни": [10432], "Хорошо Нино": [10473], "Плюшками": [10493], "СуМан": [10509], "СуБин-ом": [10510], "ХеДжун": [10517], "Сон Хо Ена": [10560], "Мм... ДжиМин": [10574], "Яйахууу": [10588], "Даа... Хо": [10592], "ЧжуВон": [10593], "Ламбада": [10651, 10754, 10755], "Виктор Цой": [10658], "Малышь": [10693], "Яхуу": [10694], "Цой": [10696, 10827], "Кукушка": [10752], "Савва Морозов": [10773], "Юрий": [10790, 11216], "Тут Нино": [10792], "Знаешь Нино": [10811], "Вон Нино": [10813], "Василий": [10816, 10899], "Василий Синайский": [10816], "Жуков": [10823], "Марк Бернес": [10850, 10870], "Газдановых": [10870], "Гамзатов": [10870, 10875], "Наум Гребнев": [10870], "Марку Бернес": [10870], "Марк Аркадьевич": [10870], "Ян Френкель": [10870], "Питер": [10878], "Исакий": [10879], "Джон Юз": [10879], "Есенин": [10879], "Юрий Григорович": [10896, 11160], "Юрий Николаевич": [10897, 10898, 10901, 10903, 11128, 11179], "Туган Сохиев": [10908, 11143], "Виктор Степанович Сорокин": [10927], "Виктор Степанович": [10928], "Степаныч": [10954, 10971, 11052, 11098, 11105, 11110, 11120, 11126], "Сергей": [10964, 10967, 10981, 10982, 11011, 11050, 11052, 11059, 11082], "Хан Тхе Иль": [10968], "Удачно": [11042], "Малышки": [11066], "Павел": [11105, 11107, 11114, 11122], "Николай": [11105, 11109, 11112, 11115, 11117, 11121], "Живящий": [11123], "Иван Грозный": [11136], "Иван": [11138], "Курбский": [11138], "Анастасия": [11138], "Сталин": [11138], "Генрих VIII": [11139], "Моцарт": [11143], "Туган": [11143], "Реквием Моцарт": [11150], "Реквием": [11153], "Караян": [11153], "Хосе! Джин": [11163], "Хан ТхеИль": [11180], "Фредди Меркюри": [11192], "Ксана Сергиенко)": [11193], "Фанфик": [11227], "О.Болдырев": [11242], "М.Николаев": [11242]}